thordata_mcp/__init__.py
thordata_mcp/aria_snapshot.py
thordata_mcp/browser_session.py
thordata_mcp/config.py
thordata_mcp/context.py
thordata_mcp/debug_http.py
thordata_mcp/main.py
thordata_mcp/monitoring.py
thordata_mcp/registry.py
thordata_mcp/utils.py
thordata_mcp/tools/__init__.py
thordata_mcp/tools/product.py
thordata_mcp/tools/product_compact.py
thordata_mcp/tools/utils.py
thordata_mcp/tools/data/__init__.py
thordata_mcp/tools/data/browser.py
thordata_mcp/tools/data/serp.py
thordata_mcp/tools/data/tasks.py
thordata_mcp/tools/data/universal.py
thordata_mcp_server-0.4.4.dist-info/METADATA
thordata_mcp_server-0.4.4.dist-info/WHEEL
thordata_mcp_server-0.4.4.dist-info/entry_points.txt
thordata_mcp_server-0.4.4.dist-info/top_level.txt
thordata_mcp_server-0.4.4.dist-info/RECORD
