Metadata-Version: 2.4
Name: thordata-mcp-server
Version: 0.4.4
Summary: Official MCP Server for Thordata.
Author-email: Thordata Developer Team <support@thordata.com>
License-Expression: MIT
Requires-Python: >=3.10
Requires-Dist: mcp[cli]>=1.0.0
Requires-Dist: sse-starlette>=1.6.1
Requires-Dist: thordata-sdk>=1.6.0
Requires-Dist: pydantic-settings
Requires-Dist: markdownify
Requires-Dist: html2text
Requires-Dist: python-dotenv
Requires-Dist: playwright>=1.40.0
Requires-Dist: beautifulsoup4>=4.12.0
Requires-Dist: anyio
Requires-Dist: starlette
Requires-Dist: uvicorn
